LICENSE.md
README.md
easycon
easycon-cli
easycon-cli.cmd
easycon.cmd
setup.py
easycon.egg-info/PKG-INFO
easycon.egg-info/SOURCES.txt
easycon.egg-info/dependency_links.txt
easycon.egg-info/requires.txt
easycon.egg-info/top_level.txt
easycon_usage/Funcs.py
easycon_usage/__init__.py