Metadata-Version: 2.1
Name: easycon
Version: 2022.2.26.1532
Summary: A tool based on paramiko used to connect to remote server.
Home-page: https://github.com/HengyueLi/easycon
Author: Hengyue Li
Author-email: hengyue.li@hengyue.li
License: LICENSE.md
Platform: UNKNOWN
Requires-Python: >=3.5
License-File: LICENSE.md
